triplix/__init__.py
triplix/__main__.py
triplix/_logging.py
triplix/config.toml
triplix/core/__init__.py
triplix/core/bam.py
triplix/core/cli.py
triplix/core/concatemers.py
triplix/core/configurations.py
triplix/core/hdf5.py
triplix/core/header.py
triplix/core/plot.py
triplix/core/stat.py
triplix/core/tri_alignments.py
triplix/core/triplets.py
triplix/core/utilities.py
triplix/core/tri_alignment/__init__.py
triplix/core/tri_alignment/extract.py
triplix/core/tri_alignment/index.py
triplix/core/tri_alignment/merge.py
triplix/core/tri_alignment/sort.py
triplix/core/triplet/__init__.py
triplix/core/triplet/bin.py
triplix/core/triplet/enrichment.py
triplix/core/triplet/kdtree.py
triplix/core/triplet/transform.py
triplix/factor_configs/distances.toml
triplix/factor_configs/pairs.toml
triplix/factor_configs/pairs_surround.toml
triplix/factor_configs/singletons.toml
triplix-0.0.5.dist-info/LICENSE
triplix-0.0.5.dist-info/METADATA
triplix-0.0.5.dist-info/WHEEL
triplix-0.0.5.dist-info/entry_points.txt
triplix-0.0.5.dist-info/top_level.txt
triplix-0.0.5.dist-info/RECORD
