Metadata-Version: 2.1
Name: triplix
Version: 0.0.5
Summary: A python package to efficiently process, store and retrieve spatial genomics multi-contact data
Author-email: Amin Allahyar <amin.allahyar@gmail.com>
License: MIT License
Project-URL: Homepage, https://github.com/deLaatLab/triplix
Keywords: Bioinformatics,Genome,3D Genome Conformation,Multi-contact
Classifier: License :: OSI Approved :: MIT License
Classifier: Programming Language :: Python
Classifier: Programming Language :: Python :: 3
Requires-Python: >=3.9
License-File: LICENSE
Requires-Dist: numpy >=1.22.2
Requires-Dist: pandas >=1.5.1
Requires-Dist: matplotlib >=3.5.1
Requires-Dist: pysam >=0.21.0
Requires-Dist: h5py >=3.7.0
Requires-Dist: joblib >=1.1.0
Requires-Dist: scipy >=1.7.3
Requires-Dist: scikit-learn >=1.1.2
Requires-Dist: pypairix >=0.3.7
Requires-Dist: igraph >=0.9.10
Requires-Dist: fasteners >=0.18
Requires-Dist: tomli ; python_version < "3.11"
